lockable/__init__.py
lockable/allocation.py
lockable/cli.py
lockable/lockable.py
lockable/provider.py
lockable/provider_file.py
lockable/provider_helpers.py
lockable/provider_http.py
lockable/provider_list.py
lockable/unflatten.py
lockable-0.13.1.dist-info/licenses/LICENSE
lockable-0.13.1.dist-info/METADATA
lockable-0.13.1.dist-info/WHEEL
lockable-0.13.1.dist-info/entry_points.txt
lockable-0.13.1.dist-info/top_level.txt
lockable-0.13.1.dist-info/RECORD
