Metadata-Version: 2.4
Name: lockable
Version: 0.13.1
Summary: lockable resource module
Home-page: https://github.com/jupe/py-lockable
Author: Jussi Vatjus-Anttila
Author-email: jussiva@gmail.com
Project-URL: Bug Reports, https://github.com/jupe/pytest-lockable
Project-URL: Source, https://github.com/jupe/pytest-lockable/
Keywords: py.test pytest lockable resource
Classifier: Development Status :: 5 - Production/Stable
Classifier: Intended Audience :: Developers
Classifier: Operating System :: POSIX
Classifier: Operating System :: Microsoft :: Windows
Classifier: Operating System :: MacOS :: MacOS X
Classifier: Topic :: Software Development :: Quality Assurance
Classifier: Topic :: Software Development :: Testing
Classifier: Topic :: Utilities
Classifier: Programming Language :: Python :: 3.9
Classifier: Programming Language :: Python :: 3.10
Classifier: Programming Language :: Python :: 3.11
Classifier: Programming Language :: Python :: 3.12
Classifier: Programming Language :: Python :: 3 :: Only
Requires-Python: >=3.9, <4
License-File: LICENSE
Requires-Dist: pid
Requires-Dist: mongo-query-match
Requires-Dist: requests
Requires-Dist: httptest
Provides-Extra: dev
Requires-Dist: pynose; extra == "dev"
Requires-Dist: coveralls; extra == "dev"
Requires-Dist: pylint; extra == "dev"
Requires-Dist: coverage; extra == "dev"
Requires-Dist: mock; extra == "dev"
Provides-Extra: optional
Requires-Dist: pytest-metadata; extra == "optional"
Dynamic: author
Dynamic: author-email
Dynamic: classifier
Dynamic: description
Dynamic: description-content-type
Dynamic: home-page
Dynamic: keywords
Dynamic: license-file
Dynamic: project-url
Dynamic: provides-extra
Dynamic: requires-dist
Dynamic: requires-python
Dynamic: summary
